cucopy/__init__.py
cucopy/currency.py
cucopy/parser.py
cucopy/utils.py
cucopy/data/currency_iso_map.yaml
cucopy/data/iso_country_map.yaml
cucopy-1.2.1.dist-info/licenses/LICENSE
cucopy-1.2.1.dist-info/METADATA
cucopy-1.2.1.dist-info/WHEEL
cucopy-1.2.1.dist-info/top_level.txt
cucopy-1.2.1.dist-info/RECORD
