Metadata-Version: 2.4
Name: cucopy
Version: 1.2.1
Summary: Module for exchanging monetary values and inflation adjustment.
Author: Julian Schönau, Jan Göpfert, Maxime Gorres, Patrick Kuckertz, Jann Weinand, Leander Kotzur, Detlef Stolten
License: MIT
Keywords: currency conversion,inflation,exchange rate,monetary,money,finance
Classifier: Development Status :: 2 - Pre-Alpha
Classifier: Programming Language :: Python :: 3
Classifier: Intended Audience :: Science/Research
Classifier: License :: OSI Approved :: MIT License
Classifier: Natural Language :: English
Classifier: Operating System :: OS Independent
Classifier: Intended Audience :: Developers
Classifier: Topic :: Scientific/Engineering
Classifier: Topic :: Utilities
Requires-Python: >=3.9
License-File: LICENSE
Requires-Dist: PyYAML>=6.0
Requires-Dist: sdmx1>=2.23.1
Requires-Dist: joblib>=1.3.2
Provides-Extra: test
Requires-Dist: pytest; extra == "test"
Dynamic: license-file
